setup.py
task_upload_dsnd_udacity/Binomialdistribution.py
task_upload_dsnd_udacity/Gaussiandistribution.py
task_upload_dsnd_udacity/Generaldistribution.py
task_upload_dsnd_udacity/__init__.py
task_upload_dsnd_udacity.egg-info/PKG-INFO
task_upload_dsnd_udacity.egg-info/SOURCES.txt
task_upload_dsnd_udacity.egg-info/dependency_links.txt
task_upload_dsnd_udacity.egg-info/not-zip-safe
task_upload_dsnd_udacity.egg-info/top_level.txt